setup.cfg
setup.py
rubidium/D1.py
rubidium/D2.py
rubidium/__init__.py
rubidium.egg-info/PKG-INFO
rubidium.egg-info/SOURCES.txt
rubidium.egg-info/dependency_links.txt
rubidium.egg-info/not-zip-safe
rubidium.egg-info/requires.txt
rubidium.egg-info/top_level.txt