Metadata-Version: 1.0
Name: rubidium
Version: 1.0
Summary: Model Rubidium D1 and D2 spectra
Home-page: http://github.com/DawesLab/rubidium
Author: Andrew M.C. Dawes
Author-email: dawes@pacificu.edu
License: GPLv3
Platform: UNKNOWN
